{
  "paths": {
    "/comments": {
      "get": {
        "deprecated": false,
        "description": "",
        "responses": {
          "200": {
            "description": "response",
            "content": {
              "application/json": {
                "schema": {
                  "type": "array",
                  "items": {
                    "$ref": "#/components/schemas/Comment"
                  }
                }
              }
            }
          },
          "403": {
            "description": "Forbidden",
            "content": {
              "application/json": {
                "schema": {
                  "$ref": "#/components/schemas/Error"
                }
              }
            }
          },
          "404": {
            "description": "Not found",
            "content": {
              "application/json": {
                "schema": {
                  "$ref": "#/components/schemas/Error"
                }
              }
            }
          },
          "default": {
            "description": "unexpected error",
            "content": {
              "application/json": {
                "schema": {
                  "$ref": "#/components/schemas/Error"
                }
              }
            }
          }
        },
        "summary": "",
        "tags": [
          "Comment"
        ],
        "parameters": [
          {
            "name": "_limit",
            "in": "query",
            "required": false,
            "description": "Maximum number of results possible",
            "schema": {
              "type": "integer"
            },
            "deprecated": false
          },
          {
            "name": "_sort",
            "in": "query",
            "required": false,
            "description": "Sort according to a specific field.",
            "schema": {
              "type": "string"
            },
            "deprecated": false
          },
          {
            "name": "_start",
            "in": "query",
            "required": false,
            "description": "Skip a specific number of entries (especially useful for pagination)",
            "schema": {
              "type": "integer"
            },
            "deprecated": false
          },
          {
            "name": "=",
            "in": "query",
            "required": false,
            "description": "Get entries that matches exactly your input",
            "schema": {
              "type": "string"
            },
            "deprecated": false
          },
          {
            "name": "_ne",
            "in": "query",
            "required": false,
            "description": "Get records that are not equals to something",
            "schema": {
              "type": "string"
            },
            "deprecated": false
          },
          {
            "name": "_lt",
            "in": "query",
            "required": false,
            "description": "Get record that are lower than a value",
            "schema": {
              "type": "string"
            },
            "deprecated": false
          },
          {
            "name": "_lte",
            "in": "query",
            "required": false,
            "description": "Get records that are lower than or equal to a value",
            "schema": {
              "type": "string"
            },
            "deprecated": false
          },
          {
            "name": "_gt",
            "in": "query",
            "required": false,
            "description": "Get records that are greater than a value",
            "schema": {
              "type": "string"
            },
            "deprecated": false
          },
          {
            "name": "_gte",
            "in": "query",
            "required": false,
            "description": "Get records that are greater than  or equal a value",
            "schema": {
              "type": "string"
            },
            "deprecated": false
          },
          {
            "name": "_contains",
            "in": "query",
            "required": false,
            "description": "Get records that contains a value",
            "schema": {
              "type": "string"
            },
            "deprecated": false
          },
          {
            "name": "_containss",
            "in": "query",
            "required": false,
            "description": "Get records that contains (case sensitive) a value",
            "schema": {
              "type": "string"
            },
            "deprecated": false
          },
          {
            "name": "_in",
            "in": "query",
            "required": false,
            "description": "Get records that matches any value in the array of values",
            "schema": {
              "type": "array"
            },
            "deprecated": false
          },
          {
            "name": "_nin",
            "in": "query",
            "required": false,
            "description": "Get records that doesn't match any value in the array of values",
            "schema": {
              "type": "array"
            },
            "deprecated": false
          }
        ]
      },
      "post": {
        "deprecated": false,
        "description": "Create a new record",
        "responses": {
          "200": {
            "description": "response",
            "content": {
              "application/json": {
                "schema": {
                  "$ref": "#/components/schemas/Comment"
                }
              }
            }
          },
          "403": {
            "description": "Forbidden",
            "content": {
              "application/json": {
                "schema": {
                  "$ref": "#/components/schemas/Error"
                }
              }
            }
          },
          "404": {
            "description": "Not found",
            "content": {
              "application/json": {
                "schema": {
                  "$ref": "#/components/schemas/Error"
                }
              }
            }
          },
          "default": {
            "description": "unexpected error",
            "content": {
              "application/json": {
                "schema": {
                  "$ref": "#/components/schemas/Error"
                }
              }
            }
          }
        },
        "summary": "",
        "tags": [
          "Comment"
        ],
        "requestBody": {
          "description": "",
          "required": true,
          "content": {
            "application/json": {
              "schema": {
                "$ref": "#/components/schemas/NewComment"
              }
            }
          }
        }
      }
    },
    "/comments/count": {
      "get": {
        "deprecated": false,
        "description": "",
        "responses": {
          "200": {
            "description": "response",
            "content": {
              "application/json": {
                "schema": {
                  "properties": {
                    "count": {
                      "type": "integer"
                    }
                  }
                }
              }
            }
          },
          "403": {
            "description": "Forbidden",
            "content": {
              "application/json": {
                "schema": {
                  "$ref": "#/components/schemas/Error"
                }
              }
            }
          },
          "404": {
            "description": "Not found",
            "content": {
              "application/json": {
                "schema": {
                  "$ref": "#/components/schemas/Error"
                }
              }
            }
          },
          "default": {
            "description": "unexpected error",
            "content": {
              "application/json": {
                "schema": {
                  "$ref": "#/components/schemas/Error"
                }
              }
            }
          }
        },
        "summary": "",
        "tags": [
          "Comment"
        ],
        "parameters": []
      }
    },
    "/comments/{_id}": {
      "get": {
        "deprecated": false,
        "description": "",
        "responses": {
          "200": {
            "description": "response",
            "content": {
              "application/json": {
                "schema": {
                  "$ref": "#/components/schemas/Comment"
                }
              }
            }
          },
          "403": {
            "description": "Forbidden",
            "content": {
              "application/json": {
                "schema": {
                  "$ref": "#/components/schemas/Error"
                }
              }
            }
          },
          "404": {
            "description": "Not found",
            "content": {
              "application/json": {
                "schema": {
                  "$ref": "#/components/schemas/Error"
                }
              }
            }
          },
          "default": {
            "description": "unexpected error",
            "content": {
              "application/json": {
                "schema": {
                  "$ref": "#/components/schemas/Error"
                }
              }
            }
          }
        },
        "summary": "",
        "tags": [
          "Comment"
        ],
        "parameters": [
          {
            "name": "_id",
            "in": "path",
            "description": "",
            "deprecated": false,
            "required": true,
            "schema": {
              "type": "string"
            }
          }
        ]
      },
      "put": {
        "deprecated": false,
        "description": "Update a record",
        "responses": {
          "200": {
            "description": "response",
            "content": {
              "application/json": {
                "schema": {
                  "$ref": "#/components/schemas/Comment"
                }
              }
            }
          },
          "403": {
            "description": "Forbidden",
            "content": {
              "application/json": {
                "schema": {
                  "$ref": "#/components/schemas/Error"
                }
              }
            }
          },
          "404": {
            "description": "Not found",
            "content": {
              "application/json": {
                "schema": {
                  "$ref": "#/components/schemas/Error"
                }
              }
            }
          },
          "default": {
            "description": "unexpected error",
            "content": {
              "application/json": {
                "schema": {
                  "$ref": "#/components/schemas/Error"
                }
              }
            }
          }
        },
        "summary": "",
        "tags": [
          "Comment"
        ],
        "requestBody": {
          "description": "",
          "required": true,
          "content": {
            "application/json": {
              "schema": {
                "$ref": "#/components/schemas/NewComment"
              }
            }
          }
        },
        "parameters": [
          {
            "name": "_id",
            "in": "path",
            "description": "",
            "deprecated": false,
            "required": true,
            "schema": {
              "type": "string"
            }
          }
        ]
      },
      "delete": {
        "deprecated": false,
        "description": "Delete a record",
        "responses": {
          "200": {
            "description": "deletes a single record based on the ID supplied",
            "content": {
              "application/json": {
                "schema": {
                  "type": "integer",
                  "format": "int64"
                }
              }
            }
          },
          "403": {
            "description": "Forbidden",
            "content": {
              "application/json": {
                "schema": {
                  "$ref": "#/components/schemas/Error"
                }
              }
            }
          },
          "404": {
            "description": "Not found",
            "content": {
              "application/json": {
                "schema": {
                  "$ref": "#/components/schemas/Error"
                }
              }
            }
          },
          "default": {
            "description": "unexpected error",
            "content": {
              "application/json": {
                "schema": {
                  "$ref": "#/components/schemas/Error"
                }
              }
            }
          }
        },
        "summary": "",
        "tags": [
          "Comment"
        ],
        "parameters": [
          {
            "name": "_id",
            "in": "path",
            "description": "",
            "deprecated": false,
            "required": true,
            "schema": {
              "type": "string"
            }
          }
        ]
      }
    }
  },
  "components": {
    "schemas": {
      "Comment": {
        "required": [
          "id"
        ],
        "properties": {
          "id": {
            "type": "string"
          },
          "text": {
            "type": "string",
            "default": "",
            "maxLength": 2000
          },
          "by": {
            "required": [
              "id",
              "handle",
              "type",
              "name"
            ],
            "properties": {
              "id": {
                "type": "string"
              },
              "handle": {
                "type": "string"
              },
              "profilePicture": {
                "type": "string"
              },
              "user": {
                "type": "string"
              },
              "likes": {
                "type": "array",
                "items": {
                  "type": "string"
                }
              },
              "type": {
                "type": "string"
              },
              "posts": {
                "type": "array",
                "items": {
                  "type": "string"
                }
              },
              "tracks": {
                "type": "array",
                "items": {
                  "type": "string"
                }
              },
              "labels": {
                "type": "array",
                "items": {
                  "type": "string"
                }
              },
              "name": {
                "type": "string"
              },
              "styles": {
                "type": "array",
                "items": {
                  "type": "string"
                }
              },
              "latitude": {
                "type": "number"
              },
              "longitude": {
                "type": "number"
              },
              "bio": {
                "type": "string"
              },
              "isPrivate": {
                "type": "boolean"
              },
              "coverPicture": {
                "type": "string"
              },
              "city": {
                "type": "string"
              },
              "country": {
                "type": "string"
              },
              "bioShort": {
                "type": "string"
              },
              "state": {
                "type": "string"
              },
              "subscriptions": {
                "type": "array",
                "items": {
                  "type": "string"
                }
              },
              "subscribers": {
                "type": "array",
                "items": {
                  "type": "string"
                }
              },
              "comments": {
                "type": "array",
                "items": {
                  "type": "string"
                }
              }
            }
          },
          "type": {
            "type": "string",
            "default": "",
            "enum": [
              "post",
              "track"
            ]
          },
          "post": {
            "required": [
              "id",
              "type",
              "content"
            ],
            "properties": {
              "id": {
                "type": "string"
              },
              "type": {
                "type": "string"
              },
              "content": {
                "type": "string"
              },
              "track": {
                "type": "string"
              },
              "likes": {
                "type": "array",
                "items": {
                  "type": "string"
                }
              },
              "profile": {
                "type": "string"
              },
              "comments": {
                "type": "array",
                "items": {
                  "type": "string"
                }
              }
            }
          },
          "track": {
            "required": [
              "id",
              "type",
              "title",
              "explicit"
            ],
            "properties": {
              "id": {
                "type": "string"
              },
              "type": {
                "type": "string"
              },
              "title": {
                "type": "string"
              },
              "edit": {
                "type": "string"
              },
              "likes": {
                "type": "array",
                "items": {
                  "type": "string"
                }
              },
              "posts": {
                "type": "array",
                "items": {
                  "type": "string"
                }
              },
              "label": {
                "type": "string"
              },
              "explicit": {
                "type": "boolean"
              },
              "audio": {
                "type": "string"
              },
              "cover": {
                "type": "string"
              },
              "description": {
                "type": "string"
              },
              "profiles": {
                "type": "array",
                "items": {
                  "type": "string"
                }
              },
              "comments": {
                "type": "array",
                "items": {
                  "type": "string"
                }
              }
            }
          },
          "trackAt": {
            "type": "integer",
            "default": ""
          }
        }
      },
      "NewComment": {
        "properties": {
          "text": {
            "type": "string",
            "default": "",
            "maxLength": 2000
          },
          "by": {
            "type": "string"
          },
          "type": {
            "type": "string",
            "default": "",
            "enum": [
              "post",
              "track"
            ]
          },
          "post": {
            "type": "string"
          },
          "track": {
            "type": "string"
          },
          "trackAt": {
            "type": "integer",
            "default": ""
          }
        }
      }
    }
  },
  "tags": [
    {
      "name": "Comment"
    }
  ]
}